clip_retrieval/__init__.py
clip_retrieval/cli.py
clip_retrieval/clip_back.py
clip_retrieval/clip_client.py
clip_retrieval/clip_end2end.py
clip_retrieval/clip_filter.py
clip_retrieval/clip_front.py
clip_retrieval/clip_index.py
clip_retrieval/h14_nsfw_model.py
clip_retrieval/ivf_metadata_ordering.py
clip_retrieval/clip_back_prepro/__init__.py
clip_retrieval/clip_back_prepro/index_combiner.py
clip_retrieval/clip_back_prepro/parquet_to_arrow.py
clip_retrieval/clip_inference/__init__.py
clip_retrieval/clip_inference/distributor.py
clip_retrieval/clip_inference/logger.py
clip_retrieval/clip_inference/main.py
clip_retrieval/clip_inference/mapper.py
clip_retrieval/clip_inference/reader.py
clip_retrieval/clip_inference/runner.py
clip_retrieval/clip_inference/slurm_distributor.py
clip_retrieval/clip_inference/slurm_worker.py
clip_retrieval/clip_inference/worker.py
clip_retrieval/clip_inference/writer.py
clip_retrieval-2.45.0.data/data/README.md
clip_retrieval-2.45.0.dist-info/licenses/LICENSE
front/build/config.json
front/build/index.html
front/build/main.16f67040.js
front/build/main.16f67040.js.LICENSE.txt
front/build/main.16f67040.js.map
front/build/assets/download.png
front/build/assets/image-search.png
front/build/assets/search.png
front/build/vendor/custom-elements-es5-adapter.js
front/build/vendor/custom-elements-es5-adapter.js.LICENSE.txt
front/build/vendor/bundles/node_modules/@webcomponents/webcomponentsjs/bundles/webcomponents-ce.js
front/build/vendor/bundles/node_modules/@webcomponents/webcomponentsjs/bundles/webcomponents-ce.js.LICENSE.txt
front/build/vendor/bundles/node_modules/@webcomponents/webcomponentsjs/bundles/webcomponents-pf_dom.js
front/build/vendor/bundles/node_modules/@webcomponents/webcomponentsjs/bundles/webcomponents-pf_dom.js.LICENSE.txt
front/build/vendor/bundles/node_modules/@webcomponents/webcomponentsjs/bundles/webcomponents-pf_js.js
front/build/vendor/bundles/node_modules/@webcomponents/webcomponentsjs/bundles/webcomponents-pf_js.js.LICENSE.txt
clip_retrieval-2.45.0.dist-info/METADATA
clip_retrieval-2.45.0.dist-info/WHEEL
clip_retrieval-2.45.0.dist-info/entry_points.txt
clip_retrieval-2.45.0.dist-info/top_level.txt
clip_retrieval-2.45.0.dist-info/RECORD
