Metadata-Version: 2.4
Name: clip_retrieval
Version: 2.45.0
Summary: Easily computing clip embeddings and building a clip retrieval system with them
Home-page: https://github.com/rom1504/clip-retrieval
Author: Romain Beaumont
Author-email: romain.rom1@gmail.com
License: MIT
Keywords: machine learning,computer vision,download,image,dataset
Classifier: Development Status :: 4 - Beta
Classifier: Intended Audience :: Developers
Classifier: Topic :: Scientific/Engineering :: Artificial Intelligence
Classifier: License :: OSI Approved :: MIT License
Classifier: Programming Language :: Python :: 3.10
Classifier: Programming Language :: Python :: 3.11
Classifier: Programming Language :: Python :: 3.12
License-File: LICENSE
Requires-Dist: img2dataset<2,>=1.46.0
Requires-Dist: clip-anytorch<3,>=2.5.0
Requires-Dist: tqdm<5,>=4.62.3
Requires-Dist: fire<0.6.0,>=0.4.0
Requires-Dist: torch<3,>=1.7.1
Requires-Dist: torchvision<2,>=0.10.1
Requires-Dist: numpy<2,>=1.19.5
Requires-Dist: faiss-cpu<2,>=1.7.2
Requires-Dist: flask<4,>=3.0.0
Requires-Dist: flask_restful<1,>=0.3.9
Requires-Dist: flask_cors<5,>=4.0.0
Requires-Dist: pandas<3,>=1.1.5
Requires-Dist: pyarrow<16,>=6.0.1
Requires-Dist: autofaiss<3,>=2.17.0
Requires-Dist: webdataset<0.3,>=0.2
Requires-Dist: h5py<4,>=3.1.0
Requires-Dist: prometheus-client<1,>=0.13.1
Requires-Dist: fsspec
Requires-Dist: sentence-transformers<3,>=2.2.0
Requires-Dist: wandb>=0.17.0
Requires-Dist: open-clip-torch<3.0.0,>=2.0.0
Requires-Dist: requests<3,>=2.28.0
Requires-Dist: aiohttp<4,>=3.8.1
Requires-Dist: multilingual-clip<2,>=1.0.10
Requires-Dist: transformers
Requires-Dist: urllib3>=1.26.0
Requires-Dist: scipy>=1.11.0
Requires-Dist: all_clip<2,>=1.3.0
Dynamic: author
Dynamic: author-email
Dynamic: classifier
Dynamic: description
Dynamic: description-content-type
Dynamic: home-page
Dynamic: keywords
Dynamic: license
Dynamic: license-file
Dynamic: requires-dist
Dynamic: summary
